[
  {
    "color" : "#FF9EF9FF",
    "tag" : "",
    "endPoint" : {
      "y" : 0.8499379,
      "x" : -0.07054022,
      "z" : -0.33543986
    },
    "points" : [
      {
        "y" : 0.88857746,
        "x" : -0.059425056,
        "z" : -0.3207258
      },
      {
        "y" : 0.8894383,
        "x" : -0.059200518,
        "z" : -0.32228294
      },
      {
        "y" : 0.8912089,
        "x" : -0.058658782,
        "z" : -0.32584727
      },
      {
        "y" : 0.8918251,
        "x" : -0.05858481,
        "z" : -0.32687894
      },
      {
        "y" : 0.89243996,
        "x" : -0.05856158,
        "z" : -0.32782277
      },
      {
        "y" : 0.8927953,
        "x" : -0.058491156,
        "z" : -0.3290692
      },
      {
        "y" : 0.8928782,
        "x" : -0.05836855,
        "z" : -0.33063817
      },
      {
        "y" : 0.8927644,
        "x" : -0.058222562,
        "z" : -0.3324145
      },
      {
        "y" : 0.89282495,
        "x" : -0.05813618,
        "z" : -0.33380294
      },
      {
        "y" : 0.89307815,
        "x" : -0.058113627,
        "z" : -0.33477286
      },
      {
        "y" : 0.89341474,
        "x" : -0.05813043,
        "z" : -0.33549967
      },
      {
        "y" : 0.89357716,
        "x" : -0.05820265,
        "z" : -0.3365136
      },
      {
        "y" : 0.89355266,
        "x" : -0.058331147,
        "z" : -0.33784178
      },
      {
        "y" : 0.8934168,
        "x" : -0.05851111,
        "z" : -0.3393278
      },
      {
        "y" : 0.8933413,
        "x" : -0.058831483,
        "z" : -0.3405714
      },
      {
        "y" : 0.8933346,
        "x" : -0.059296794,
        "z" : -0.34155232
      },
      {
        "y" : 0.89334583,
        "x" : -0.059880763,
        "z" : -0.34238827
      },
      {
        "y" : 0.8934207,
        "x" : -0.06037139,
        "z" : -0.34329918
      },
      {
        "y" : 0.89356107,
        "x" : -0.06075791,
        "z" : -0.34429595
      },
      {
        "y" : 0.8937543,
        "x" : -0.06110276,
        "z" : -0.34531388
      },
      {
        "y" : 0.8939814,
        "x" : -0.061479356,
        "z" : -0.346298
      },
      {
        "y" : 0.8942404,
        "x" : -0.06189137,
        "z" : -0.34724492
      },
      {
        "y" : 0.8945376,
        "x" : -0.062317178,
        "z" : -0.34817138
      },
      {
        "y" : 0.89484805,
        "x" : -0.06275629,
        "z" : -0.34910974
      },
      {
        "y" : 0.89517075,
        "x" : -0.06320869,
        "z" : -0.35006195
      },
      {
        "y" : 0.8955127,
        "x" : -0.06367454,
        "z" : -0.35101828
      },
      {
        "y" : 0.8959104,
        "x" : -0.0642678,
        "z" : -0.35169843
      },
      {
        "y" : 0.896365,
        "x" : -0.0649942,
        "z" : -0.35208827
      },
      {
        "y" : 0.8968667,
        "x" : -0.06582019,
        "z" : -0.35227045
      },
      {
        "y" : 0.8973875,
        "x" : -0.06661954,
        "z" : -0.35232452
      },
      {
        "y" : 0.8979259,
        "x" : -0.06738581,
        "z" : -0.3522544
      },
      {
        "y" : 0.89849037,
        "x" : -0.068156175,
        "z" : -0.35203677
      },
      {
        "y" : 0.89895976,
        "x" : -0.069041975,
        "z" : -0.3517077
      },
      {
        "y" : 0.8993285,
        "x" : -0.07004883,
        "z" : -0.3512693
      },
      {
        "y" : 0.89963156,
        "x" : -0.07114386,
        "z" : -0.35071057
      },
      {
        "y" : 0.89985085,
        "x" : -0.072098896,
        "z" : -0.3504354
      },
      {
        "y" : 0.89998525,
        "x" : -0.07290224,
        "z" : -0.35046402
      },
      {
        "y" : 0.90004,
        "x" : -0.07362127,
        "z" : -0.3506775
      },
      {
        "y" : 0.90013176,
        "x" : -0.07425631,
        "z" : -0.3510065
      },
      {
        "y" : 0.90026623,
        "x" : -0.0748073,
        "z" : -0.35144737
      },
      {
        "y" : 0.90040934,
        "x" : -0.07527429,
        "z" : -0.35202065
      },
      {
        "y" : 0.90068424,
        "x" : -0.07582087,
        "z" : -0.35233507
      },
      {
        "y" : 0.90109724,
        "x" : -0.07645523,
        "z" : -0.352371
      },
      {
        "y" : 0.90161157,
        "x" : -0.077129155,
        "z" : -0.35224354
      },
      {
        "y" : 0.9022149,
        "x" : -0.077673666,
        "z" : -0.35259616
      },
      {
        "y" : 0.90290546,
        "x" : -0.0780803,
        "z" : -0.3534607
      },
      {
        "y" : 0.9036876,
        "x" : -0.078398734,
        "z" : -0.3546479
      },
      {
        "y" : 0.90489566,
        "x" : -0.078651674,
        "z" : -0.35665044
      },
      {
        "y" : 0.90654683,
        "x" : -0.078840196,
        "z" : -0.35949308
      },
      {
        "y" : 0.9085424,
        "x" : -0.078957744,
        "z" : -0.36303055
      },
      {
        "y" : 0.91096646,
        "x" : -0.07932748,
        "z" : -0.36576065
      },
      {
        "y" : 0.9138228,
        "x" : -0.07996549,
        "z" : -0.36760858
      },
      {
        "y" : 0.9170869,
        "x" : -0.08077668,
        "z" : -0.3690163
      },
      {
        "y" : 0.92046857,
        "x" : -0.08149866,
        "z" : -0.37082696
      },
      {
        "y" : 0.9239528,
        "x" : -0.082118385,
        "z" : -0.37308252
      },
      {
        "y" : 0.9276231,
        "x" : -0.082712635,
        "z" : -0.37553322
      },
      {
        "y" : 0.9317232,
        "x" : -0.08340059,
        "z" : -0.37791806
      },
      {
        "y" : 0.93626237,
        "x" : -0.08418787,
        "z" : -0.38022143
      },
      {
        "y" : 0.9411708,
        "x" : -0.08503964,
        "z" : -0.3825217
      },
      {
        "y" : 0.9461339,
        "x" : -0.086028524,
        "z" : -0.38477644
      },
      {
        "y" : 0.95113605,
        "x" : -0.08715833,
        "z" : -0.38698357
      },
      {
        "y" : 0.9562701,
        "x" : -0.088407665,
        "z" : -0.38915575
      },
      {
        "y" : 0.96130943,
        "x" : -0.089629695,
        "z" : -0.39134583
      },
      {
        "y" : 0.9662416,
        "x" : -0.09081683,
        "z" : -0.3935563
      },
      {
        "y" : 0.97113407,
        "x" : -0.09201245,
        "z" : -0.39577186
      },
      {
        "y" : 0.97649777,
        "x" : -0.09300172,
        "z" : -0.3985005
      },
      {
        "y" : 0.98235875,
        "x" : -0.093773834,
        "z" : -0.40176806
      },
      {
        "y" : 0.98856634,
        "x" : -0.0943919,
        "z" : -0.40542483
      },
      {
        "y" : 0.9947685,
        "x" : -0.0952292,
        "z" : -0.4087232
      },
      {
        "y" : 1.0009465,
        "x" : -0.09630459,
        "z" : -0.41162476
      },
      {
        "y" : 1.0072044,
        "x" : -0.09750808,
        "z" : -0.41435015
      },
      {
        "y" : 1.0191896,
        "x" : -0.09923981,
        "z" : -0.41884133
      },
      {
        "y" : 1.0249777,
        "x" : -0.09985274,
        "z" : -0.4206414
      },
      {
        "y" : 1.0307616,
        "x" : -0.100360915,
        "z" : -0.42237613
      },
      {
        "y" : 1.036549,
        "x" : -0.10076603,
        "z" : -0.4240576
      },
      {
        "y" : 1.0423068,
        "x" : -0.10105918,
        "z" : -0.42562088
      },
      {
        "y" : 1.0481524,
        "x" : -0.101357125,
        "z" : -0.42679167
      },
      {
        "y" : 1.0540923,
        "x" : -0.10166594,
        "z" : -0.42755604
      },
      {
        "y" : 1.060092,
        "x" : -0.101951115,
        "z" : -0.42799515
      },
      {
        "y" : 1.066217,
        "x" : -0.10212643,
        "z" : -0.42895257
      },
      {
        "y" : 1.0724719,
        "x" : -0.10218767,
        "z" : -0.43047172
      },
      {
        "y" : 1.0788366,
        "x" : -0.102160074,
        "z" : -0.43230367
      },
      {
        "y" : 1.0852631,
        "x" : -0.10196424,
        "z" : -0.43387216
      },
      {
        "y" : 1.0917495,
        "x" : -0.10159595,
        "z" : -0.4351482
      },
      {
        "y" : 1.09831,
        "x" : -0.1010788,
        "z" : -0.4363015
      },
      {
        "y" : 1.1045336,
        "x" : -0.10035644,
        "z" : -0.4371361
      },
      {
        "y" : 1.1104,
        "x" : -0.099425994,
        "z" : -0.4376418
      },
      {
        "y" : 1.1160305,
        "x" : -0.09830407,
        "z" : -0.43787685
      },
      {
        "y" : 1.1215363,
        "x" : -0.096820086,
        "z" : -0.43794417
      },
      {
        "y" : 1.1269221,
        "x" : -0.094965294,
        "z" : -0.43784884
      },
      {
        "y" : 1.1321563,
        "x" : -0.09279001,
        "z" : -0.43756068
      },
      {
        "y" : 1.1371758,
        "x" : -0.09047176,
        "z" : -0.4371185
      },
      {
        "y" : 1.1419779,
        "x" : -0.08801961,
        "z" : -0.4365246
      },
      {
        "y" : 1.1465807,
        "x" : -0.08538109,
        "z" : -0.4357672
      },
      {
        "y" : 1.1507386,
        "x" : -0.08261611,
        "z" : -0.4350491
      },
      {
        "y" : 1.1544391,
        "x" : -0.079727665,
        "z" : -0.43438047
      },
      {
        "y" : 1.1577549,
        "x" : -0.07669807,
        "z" : -0.43370175
      },
      {
        "y" : 1.1602708,
        "x" : -0.07353876,
        "z" : -0.43269187
      },
      {
        "y" : 1.1619658,
        "x" : -0.07025036,
        "z" : -0.4313347
      },
      {
        "y" : 1.1629622,
        "x" : -0.066829436,
        "z" : -0.42972475
      },
      {
        "y" : 1.1639076,
        "x" : -0.06354352,
        "z" : -0.42810124
      },
      {
        "y" : 1.164834,
        "x" : -0.060406134,
        "z" : -0.42647594
      },
      {
        "y" : 1.165551,
        "x" : -0.0573384,
        "z" : -0.4247786
      },
      {
        "y" : 1.1652691,
        "x" : -0.054288775,
        "z" : -0.4237097
      },
      {
        "y" : 1.1618228,
        "x" : -0.048251696,
        "z" : -0.4233553
      },
      {
        "y" : 1.1587604,
        "x" : -0.045928203,
        "z" : -0.42256838
      },
      {
        "y" : 1.154754,
        "x" : -0.044316564,
        "z" : -0.4208782
      },
      {
        "y" : 1.1498425,
        "x" : -0.043225966,
        "z" : -0.41866624
      },
      {
        "y" : 1.1445432,
        "x" : -0.04239692,
        "z" : -0.4172279
      },
      {
        "y" : 1.1388853,
        "x" : -0.041816916,
        "z" : -0.41662782
      },
      {
        "y" : 1.1327096,
        "x" : -0.041561462,
        "z" : -0.4164844
      },
      {
        "y" : 1.1263449,
        "x" : -0.04138402,
        "z" : -0.41640633
      },
      {
        "y" : 1.1198081,
        "x" : -0.041271854,
        "z" : -0.41637373
      },
      {
        "y" : 1.1130029,
        "x" : -0.04129787,
        "z" : -0.4165021
      },
      {
        "y" : 1.1059079,
        "x" : -0.04144885,
        "z" : -0.4163238
      },
      {
        "y" : 1.0985229,
        "x" : -0.041724086,
        "z" : -0.41581538
      },
      {
        "y" : 1.0908538,
        "x" : -0.042127438,
        "z" : -0.41511458
      },
      {
        "y" : 1.0833619,
        "x" : -0.042519115,
        "z" : -0.4146471
      },
      {
        "y" : 1.0760707,
        "x" : -0.04289207,
        "z" : -0.41443494
      },
      {
        "y" : 1.0688441,
        "x" : -0.04328736,
        "z" : -0.41435233
      },
      {
        "y" : 1.0616828,
        "x" : -0.04357133,
        "z" : -0.4141414
      },
      {
        "y" : 1.0545866,
        "x" : -0.04373712,
        "z" : -0.41378897
      },
      {
        "y" : 1.0475553,
        "x" : -0.04382412,
        "z" : -0.4133712
      },
      {
        "y" : 1.041258,
        "x" : -0.044141006,
        "z" : -0.4129235
      },
      {
        "y" : 1.0357292,
        "x" : -0.0447034,
        "z" : -0.41244793
      },
      {
        "y" : 1.0307713,
        "x" : -0.04542032,
        "z" : -0.4119339
      },
      {
        "y" : 1.026906,
        "x" : -0.045994997,
        "z" : -0.41182542
      },
      {
        "y" : 1.0241585,
        "x" : -0.04641222,
        "z" : -0.41214484
      },
      {
        "y" : 1.0223762,
        "x" : -0.046759628,
        "z" : -0.41276115
      },
      {
        "y" : 1.0222964,
        "x" : -0.04712096,
        "z" : -0.41321516
      },
      {
        "y" : 1.0239563,
        "x" : -0.047500443,
        "z" : -0.41348308
      },
      {
        "y" : 1.0271397,
        "x" : -0.047873504,
        "z" : -0.4137007
      },
      {
        "y" : 1.0312172,
        "x" : -0.047743548,
        "z" : -0.41415027
      },
      {
        "y" : 1.0361583,
        "x" : -0.047085434,
        "z" : -0.4148464
      },
      {
        "y" : 1.0421472,
        "x" : -0.046045467,
        "z" : -0.4157056
      },
      {
        "y" : 1.0485002,
        "x" : -0.044828735,
        "z" : -0.4161602
      },
      {
        "y" : 1.055183,
        "x" : -0.043445565,
        "z" : -0.41618174
      },
      {
        "y" : 1.0623971,
        "x" : -0.041835636,
        "z" : -0.4159373
      },
      {
        "y" : 1.0699098,
        "x" : -0.03975222,
        "z" : -0.4161343
      },
      {
        "y" : 1.0777088,
        "x" : -0.03718286,
        "z" : -0.41680825
      },
      {
        "y" : 1.0858625,
        "x" : -0.034200232,
        "z" : -0.41775087
      },
      {
        "y" : 1.0937479,
        "x" : -0.03060484,
        "z" : -0.41835478
      },
      {
        "y" : 1.1013322,
        "x" : -0.026386408,
        "z" : -0.41858912
      },
      {
        "y" : 1.1088002,
        "x" : -0.021603964,
        "z" : -0.41863325
      },
      {
        "y" : 1.1159213,
        "x" : -0.016753547,
        "z" : -0.41821963
      },
      {
        "y" : 1.1226835,
        "x" : -0.0118604,
        "z" : -0.41733474
      },
      {
        "y" : 1.1291548,
        "x" : -0.0067782486,
        "z" : -0.41605735
      },
      {
        "y" : 1.1351268,
        "x" : -0.0014408166,
        "z" : -0.4149674
      },
      {
        "y" : 1.1405885,
        "x" : 0.0041552144,
        "z" : -0.41409385
      },
      {
        "y" : 1.1456016,
        "x" : 0.0099903345,
        "z" : -0.4132659
      },
      {
        "y" : 1.1497122,
        "x" : 0.015964383,
        "z" : -0.41223094
      },
      {
        "y" : 1.1528976,
        "x" : 0.022072362,
        "z" : -0.41097587
      },
      {
        "y" : 1.1552912,
        "x" : 0.028343622,
        "z" : -0.4095752
      },
      {
        "y" : 1.1570367,
        "x" : 0.034500606,
        "z" : -0.4087291
      },
      {
        "y" : 1.1581397,
        "x" : 0.040529482,
        "z" : -0.40847212
      },
      {
        "y" : 1.1585592,
        "x" : 0.04651193,
        "z" : -0.40859854
      },
      {
        "y" : 1.1581676,
        "x" : 0.051575873,
        "z" : -0.40756726
      },
      {
        "y" : 1.1569594,
        "x" : 0.055678207,
        "z" : -0.40530148
      },
      {
        "y" : 1.1549716,
        "x" : 0.059075277,
        "z" : -0.40225476
      },
      {
        "y" : 1.1528095,
        "x" : 0.06256431,
        "z" : -0.40085107
      },
      {
        "y" : 1.1505026,
        "x" : 0.06618514,
        "z" : -0.40121078
      },
      {
        "y" : 1.1478738,
        "x" : 0.06970315,
        "z" : -0.4026212
      },
      {
        "y" : 1.1449155,
        "x" : 0.07277797,
        "z" : -0.40313974
      },
      {
        "y" : 1.1416276,
        "x" : 0.075392686,
        "z" : -0.40267
      },
      {
        "y" : 1.1380154,
        "x" : 0.0776462,
        "z" : -0.40178436
      },
      {
        "y" : 1.1338164,
        "x" : 0.07917072,
        "z" : -0.40088668
      },
      {
        "y" : 1.1290206,
        "x" : 0.07994549,
        "z" : -0.39999837
      },
      {
        "y" : 1.1237031,
        "x" : 0.08008001,
        "z" : -0.39899978
      },
      {
        "y" : 1.1180652,
        "x" : 0.07994305,
        "z" : -0.3980442
      },
      {
        "y" : 1.1121172,
        "x" : 0.07955347,
        "z" : -0.39713913
      },
      {
        "y" : 1.1057993,
        "x" : 0.07880249,
        "z" : -0.39623964
      },
      {
        "y" : 1.1001767,
        "x" : 0.07831517,
        "z" : -0.39575362
      },
      {
        "y" : 1.0953035,
        "x" : 0.07812342,
        "z" : -0.3957016
      },
      {
        "y" : 1.0908663,
        "x" : 0.07804297,
        "z" : -0.39596373
      },
      {
        "y" : 1.0851886,
        "x" : 0.07712454,
        "z" : -0.395734
      },
      {
        "y" : 1.078186,
        "x" : 0.07531966,
        "z" : -0.39497146
      },
      {
        "y" : 1.0703515,
        "x" : 0.07290833,
        "z" : -0.39391357
      },
      {
        "y" : 1.0635297,
        "x" : 0.07025829,
        "z" : -0.3934816
      },
      {
        "y" : 1.0578152,
        "x" : 0.06738838,
        "z" : -0.39372256
      },
      {
        "y" : 1.0526631,
        "x" : 0.06419014,
        "z" : -0.3943645
      },
      {
        "y" : 1.0472078,
        "x" : 0.06092687,
        "z" : -0.39469048
      },
      {
        "y" : 1.0414048,
        "x" : 0.057611868,
        "z" : -0.39466384
      },
      {
        "y" : 1.0355102,
        "x" : 0.054167613,
        "z" : -0.39449614
      },
      {
        "y" : 1.0299424,
        "x" : 0.05071897,
        "z" : -0.39476714
      },
      {
        "y" : 1.0247215,
        "x" : 0.04727108,
        "z" : -0.3955063
      },
      {
        "y" : 1.0197252,
        "x" : 0.043787844,
        "z" : -0.3965428
      },
      {
        "y" : 1.0144506,
        "x" : 0.03987485,
        "z" : -0.39720201
      },
      {
        "y" : 1.0088725,
        "x" : 0.035512038,
        "z" : -0.39744973
      },
      {
        "y" : 1.0031393,
        "x" : 0.030815687,
        "z" : -0.3974849
      },
      {
        "y" : 0.99721944,
        "x" : 0.026115928,
        "z" : -0.3969378
      },
      {
        "y" : 0.9911126,
        "x" : 0.021429498,
        "z" : -0.3957903
      },
      {
        "y" : 0.9848274,
        "x" : 0.016659208,
        "z" : -0.39415097
      },
      {
        "y" : 0.97879964,
        "x" : 0.011911567,
        "z" : -0.39311367
      },
      {
        "y" : 0.9730518,
        "x" : 0.007191953,
        "z" : -0.39273405
      },
      {
        "y" : 0.9674551,
        "x" : 0.0024688959,
        "z" : -0.3926898
      },
      {
        "y" : 0.9617945,
        "x" : -0.0023416255,
        "z" : -0.39212447
      },
      {
        "y" : 0.9560585,
        "x" : -0.0072438293,
        "z" : -0.39099467
      },
      {
        "y" : 0.9503112,
        "x" : -0.012213108,
        "z" : -0.38955286
      },
      {
        "y" : 0.9443574,
        "x" : -0.017289938,
        "z" : -0.3879576
      },
      {
        "y" : 0.93818754,
        "x" : -0.022476405,
        "z" : -0.38621706
      },
      {
        "y" : 0.93185854,
        "x" : -0.027760662,
        "z" : -0.38428426
      },
      {
        "y" : 0.92524844,
        "x" : -0.0329416,
        "z" : -0.38199964
      },
      {
        "y" : 0.9183505,
        "x" : -0.038009003,
        "z" : -0.37935495
      },
      {
        "y" : 0.9112016,
        "x" : -0.04302226,
        "z" : -0.3763976
      },
      {
        "y" : 0.90431964,
        "x" : -0.047837146,
        "z" : -0.37331915
      },
      {
        "y" : 0.8977307,
        "x" : -0.052446302,
        "z" : -0.3701294
      },
      {
        "y" : 0.8912823,
        "x" : -0.056892343,
        "z" : -0.36677182
      },
      {
        "y" : 0.8853237,
        "x" : -0.060787182,
        "z" : -0.3634351
      },
      {
        "y" : 0.87987155,
        "x" : -0.064111345,
        "z" : -0.36012852
      },
      {
        "y" : 0.8748242,
        "x" : -0.066979006,
        "z" : -0.35679704
      },
      {
        "y" : 0.8700538,
        "x" : -0.06935558,
        "z" : -0.35418457
      },
      {
        "y" : 0.86555475,
        "x" : -0.07123925,
        "z" : -0.35232887
      },
      {
        "y" : 0.8613645,
        "x" : -0.07264028,
        "z" : -0.3510106
      },
      {
        "y" : 0.85752785,
        "x" : -0.07359193,
        "z" : -0.34968805
      },
      {
        "y" : 0.85404783,
        "x" : -0.07409591,
        "z" : -0.3483343
      },
      {
        "y" : 0.85091037,
        "x" : -0.074142344,
        "z" : -0.34710875
      },
      {
        "y" : 0.8485178,
        "x" : -0.07419013,
        "z" : -0.34584838
      },
      {
        "y" : 0.8468906,
        "x" : -0.074262135,
        "z" : -0.3445455
      },
      {
        "y" : 0.84590954,
        "x" : -0.07422322,
        "z" : -0.34324744
      },
      {
        "y" : 0.84525734,
        "x" : -0.07403453,
        "z" : -0.34219503
      },
      {
        "y" : 0.8449165,
        "x" : -0.07369358,
        "z" : -0.3413985
      },
      {
        "y" : 0.8449818,
        "x" : -0.07321219,
        "z" : -0.3407883
      },
      {
        "y" : 0.8452581,
        "x" : -0.07273206,
        "z" : -0.34000748
      },
      {
        "y" : 0.84573567,
        "x" : -0.072260536,
        "z" : -0.3390379
      },
      {
        "y" : 0.8464714,
        "x" : -0.07175571,
        "z" : -0.33798465
      },
      {
        "y" : 0.84724057,
        "x" : -0.07132735,
        "z" : -0.33710682
      },
      {
        "y" : 0.84803104,
        "x" : -0.070981055,
        "z" : -0.33641776
      },
      {
        "y" : 0.84890974,
        "x" : -0.07068445,
        "z" : -0.3358411
      },
      {
        "y" : 0.8499379,
        "x" : -0.07054022,
        "z" : -0.33543986
      }
    ],
    "startPoint" : {
      "y" : 0.88857746,
      "x" : -0.059425056,
      "z" : -0.3207258
    }
  }
]